imx/__init__.py
imx/hab/__init__.py
imx/hab/enums.py
imx/hab/parser.py
imx/img/__init__.py
imx/img/__main__.py
imx/img/commands.py
imx/img/header.py
imx/img/images.py
imx/img/misc.py
imx/img/secret.py
imx/img/segments.py
imx/otp/__init__.py
imx/otp/fuses.py
imx/sdp/__init__.py
imx/sdp/__main__.py
imx/sdp/misc.py
imx/sdp/sdp.py
imx/sdp/usb.py
imx-0.1.3.dist-info/LICENSE
imx-0.1.3.dist-info/METADATA
imx-0.1.3.dist-info/WHEEL
imx-0.1.3.dist-info/entry_points.txt
imx-0.1.3.dist-info/top_level.txt
imx-0.1.3.dist-info/RECORD
