Metadata-Version: 2.1
Name: imx
Version: 0.1.3
Summary: Open Source library for easy development with i.MX platform
Home-page: https://github.com/molejar/pyIMX
Author: Martin Olejar
Author-email: martin.olejar@gmail.com
License: BSD3
Platform: Windows
Platform: Linux
Classifier: Programming Language :: Python :: 3
Classifier: Operating System :: POSIX :: Linux
Classifier: Operating System :: Microsoft :: Windows
Classifier: License :: OSI Approved :: BSD License
Classifier: Topic :: Scientific/Engineering
Classifier: Topic :: Software Development :: Embedded Systems
Classifier: Topic :: System :: Hardware
Classifier: Topic :: Utilities
Requires-Python: >=3.5
Requires-Dist: click (==7.0)
Requires-Dist: PyYAML (==5.1.1)
Requires-Dist: bincopy (==16.0.0)
Requires-Dist: easy-enum (==0.2.0)
Requires-Dist: cryptography (==2.6.1)
Requires-Dist: pyusb (==1.0.0) ; platform_system != "Windows"
Requires-Dist: pywinusb (==0.4.2) ; platform_system == "Windows"
